MANIFEST.in
setup.py
scripts/deploygame
scripts/deploygame.bat
scripts/local_server
scripts/local_server.bat
turbulenz_local/__init__.py
turbulenz_local/decorators.py
turbulenz_local/deploygame.py
turbulenz_local/helpers.py
turbulenz_local/local_server.py
turbulenz_local/paste_factory.py
turbulenz_local/routing.py
turbulenz_local/tools.py
turbulenz_local/wsgiapp.py
turbulenz_local.egg-info/PKG-INFO
turbulenz_local.egg-info/SOURCES.txt
turbulenz_local.egg-info/dependency_links.txt
turbulenz_local.egg-info/not-zip-safe
turbulenz_local.egg-info/requires.txt
turbulenz_local.egg-info/top_level.txt
turbulenz_local/config/common.ini
turbulenz_local/config/css_versions.yaml
turbulenz_local/config/defaultgames.yaml
turbulenz_local/config/defaultusers.yaml
turbulenz_local/config/development.ini
turbulenz_local/config/html_versions.yaml
turbulenz_local/config/js_versions.yaml
turbulenz_local/config/release.ini
turbulenz_local/controllers/__init__.py
turbulenz_local/controllers/disassembler.py
turbulenz_local/controllers/viewer.py
turbulenz_local/controllers/apiv1/__init__.py
turbulenz_local/controllers/apiv1/badges.py
turbulenz_local/controllers/apiv1/custommetrics.py
turbulenz_local/controllers/apiv1/datashare.py
turbulenz_local/controllers/apiv1/gameauthtoken.py
turbulenz_local/controllers/apiv1/gamenotifications.py
turbulenz_local/controllers/apiv1/gameprofile.py
turbulenz_local/controllers/apiv1/games.py
turbulenz_local/controllers/apiv1/leaderboards.py
turbulenz_local/controllers/apiv1/multiplayer.py
turbulenz_local/controllers/apiv1/profiles.py
turbulenz_local/controllers/apiv1/servicestatus.py
turbulenz_local/controllers/apiv1/store.py
turbulenz_local/controllers/apiv1/userdata.py
turbulenz_local/controllers/localv1/__init__.py
turbulenz_local/controllers/localv1/deploy.py
turbulenz_local/controllers/localv1/edit.py
turbulenz_local/controllers/localv1/games.py
turbulenz_local/controllers/localv1/list.py
turbulenz_local/controllers/localv1/metrics.py
turbulenz_local/controllers/localv1/play.py
turbulenz_local/controllers/localv1/user.py
turbulenz_local/controllers/localv1/userdata.py
turbulenz_local/handlers/__init__.py
turbulenz_local/handlers/localv1/__init__.py
