Metadata-Version: 1.1
Name: turbulenz-local
Version: 1.1.6
Summary: Turbulenz Local Development Web Server
Home-page: https://turbulenz.com/
Author: Turbulenz Limited
Author-email: support@turbulenz.com
License: MIT
Platform: Posix; MacOS X; Windows
Classifier: Development Status :: 5 - Production/Stable
Classifier: Intended Audience :: Developers
Classifier: License :: OSI Approved :: MIT License
Classifier: Operating System :: OS Independent
Classifier: Topic :: Software Development
Classifier: Programming Language :: Python :: 2.7
